[
    {
        "key": "dbln",
        "value": "%7B%22100091751222277%22%3A%22lo07uqxp%22%2C%2261561079154975%22%3A%22wUmcwbHM%22%2C%22100092010643066%22%3A%22YYVhG65l%22%2C%2261560934622044%22%3A%22MjKSCwnb%22%2C%22100043355861492%22%3A%22ZdrPnz0p%22%7D",
        "domain": "facebook.com",
        "path": "/login/device-based/",
        "hostOnly": false,
        "creation": "2024-07-02T03:01:07.909Z",
        "lastAccessed": "2024-07-02T03:01:07.910Z"
    },
    {
        "key": "datr",
        "value": "y6GBZdQg-yomwufZPpMoApwv",
        "domain": "facebook.com",
        "path": "/",
        "hostOnly": false,
        "creation": "2024-07-02T03:01:07.910Z",
        "lastAccessed": "2024-07-02T03:01:07.910Z"
    },
    {
        "key": "sb",
        "value": "y6GBZeLEyURnoUiIpvogaJWA",
        "domain": "facebook.com",
        "path": "/",
        "hostOnly": false,
        "creation": "2024-07-02T03:01:07.910Z",
        "lastAccessed": "2024-07-02T03:01:07.910Z"
    },
    {
        "key": "ps_n",
        "value": "1",
        "domain": "facebook.com",
        "path": "/",
        "hostOnly": false,
        "creation": "2024-07-02T03:01:07.910Z",
        "lastAccessed": "2024-07-02T03:01:07.910Z"
    },
    {
        "key": "ps_l",
        "value": "1",
        "domain": "facebook.com",
        "path": "/",
        "hostOnly": false,
        "creation": "2024-07-02T03:01:07.910Z",
        "lastAccessed": "2024-07-02T03:01:07.910Z"
    },
    {
        "key": "vpd",
        "value": "v1%3B669x333x2.157599449157715",
        "domain": "facebook.com",
        "path": "/",
        "hostOnly": false,
        "creation": "2024-07-02T03:01:07.910Z",
        "lastAccessed": "2024-07-02T03:01:07.910Z"
    },
    {
        "key": "dpr",
        "value": "2.157599449157715",
        "domain": "facebook.com",
        "path": "/",
        "hostOnly": false,
        "creation": "2024-07-02T03:01:07.910Z",
        "lastAccessed": "2024-07-02T03:01:07.910Z"
    },
    {
        "key": "locale",
        "value": "en_GB",
        "domain": "facebook.com",
        "path": "/",
        "hostOnly": false,
        "creation": "2024-07-02T03:01:07.910Z",
        "lastAccessed": "2024-07-02T03:01:07.910Z"
    },
    {
        "key": "m_pixel_ratio",
        "value": "2.157599449157715",
        "domain": "facebook.com",
        "path": "/",
        "hostOnly": false,
        "creation": "2024-07-02T03:01:07.910Z",
        "lastAccessed": "2024-07-02T03:01:07.910Z"
    },
    {
        "key": "wd",
        "value": "334x669",
        "domain": "facebook.com",
        "path": "/",
        "hostOnly": false,
        "creation": "2024-07-02T03:01:07.910Z",
        "lastAccessed": "2024-07-02T03:01:07.910Z"
    },
    {
        "key": "fr",
        "value": "0oiGDdDTQbdIRPz8F.AWXz4G1LLWTbnYvp1M-cW9o0VGA.BlgaHL..AAA.0.0.Bmg21j.AWV_uIyylLg",
        "domain": "facebook.com",
        "path": "/",
        "hostOnly": false,
        "creation": "2024-07-02T03:01:07.910Z",
        "lastAccessed": "2024-07-02T03:01:07.910Z"
    },
    {
        "key": "c_user",
        "value": "100092010643066",
        "domain": "facebook.com",
        "path": "/",
        "hostOnly": false,
        "creation": "2024-07-02T03:01:07.910Z",
        "lastAccessed": "2024-07-02T03:01:07.910Z"
    },
    {
        "key": "xs",
        "value": "8%3A4_x3beqBU5iCNA%3A2%3A1719889252%3A-1%3A12989",
        "domain": "facebook.com",
        "path": "/",
        "hostOnly": false,
        "creation": "2024-07-02T03:01:07.910Z",
        "lastAccessed": "2024-07-02T03:01:07.910Z"
    },
    {
        "key": "fbl_st",
        "value": "101437648%3BT%3A28664821",
        "domain": "facebook.com",
        "path": "/",
        "hostOnly": false,
        "creation": "2024-07-02T03:01:07.910Z",
        "lastAccessed": "2024-07-02T03:01:07.910Z"
    },
    {
        "key": "wl_cbv",
        "value": "v2%3Bclient_version%3A2549%3Btimestamp%3A1719889261",
        "domain": "facebook.com",
        "path": "/",
        "hostOnly": false,
        "creation": "2024-07-02T03:01:07.910Z",
        "lastAccessed": "2024-07-02T03:01:07.910Z"
    }
]
